multiset_multicover/__init__.py
multiset_multicover/_c_multiset_multicover.cp311-win_amd64.pyd
multiset_multicover/python_source.py
multiset_multicover-1.0.dist-info/LICENSE
multiset_multicover-1.0.dist-info/METADATA
multiset_multicover-1.0.dist-info/WHEEL
multiset_multicover-1.0.dist-info/top_level.txt
multiset_multicover-1.0.dist-info/RECORD
